prolothar_process_discovery/__init__.py
prolothar_process_discovery/anomalydetection/__init__.py
prolothar_process_discovery/anomalydetection/oc3.py
prolothar_process_discovery/anomalydetection/pdfg_oc3.py
prolothar_process_discovery/anomalydetection/traces/__init__.py
prolothar_process_discovery/anomalydetection/traces/mst.py
prolothar_process_discovery/anomalydetection/traces/proseqo_oc3.py
prolothar_process_discovery/anomalydetection/traces/proseqo_supervised.py
prolothar_process_discovery/anomalydetection/traces/supervised_detector.py
prolothar_process_discovery/anomalydetection/traces/unsupervised_detector.py
prolothar_process_discovery/conformance/__init__.py
prolothar_process_discovery/conformance/data_petri_net_conformance.py
prolothar_process_discovery/conformance/logdistance/__init__.py
prolothar_process_discovery/conformance/logdistance/abstract_min_edit_distance.py
prolothar_process_discovery/conformance/logdistance/greedy_min_edit_distance.py
prolothar_process_discovery/conformance/logdistance/naive_min_edit_distance.py
prolothar_process_discovery/conformance/logdistance/pdfg_log_distance.py
prolothar_process_discovery/conformance/logdistance/trace_to_characters_translator.py
prolothar_process_discovery/data/__init__.py
prolothar_process_discovery/data/synthetic_baking/__init__.py
prolothar_process_discovery/data/synthetic_baking/baking.py
prolothar_process_discovery/discovery/__init__.py
prolothar_process_discovery/discovery/proseqo/__init__.py
prolothar_process_discovery/discovery/proseqo/cover.py
prolothar_process_discovery/discovery/proseqo/cover_traces_for_statistics.py
prolothar_process_discovery/discovery/proseqo/greedy_cover.py
prolothar_process_discovery/discovery/proseqo/mdl_score.py
prolothar_process_discovery/discovery/proseqo/mdl_score_dfg.py
prolothar_process_discovery/discovery/proseqo/pattern_dfg.py
prolothar_process_discovery/discovery/proseqo/submodel_detector.py
prolothar_process_discovery/discovery/proseqo/clustering/__init__.py
prolothar_process_discovery-6.0.0.dist-info/LICENSE
prolothar_process_discovery-6.0.0.dist-info/METADATA
prolothar_process_discovery-6.0.0.dist-info/WHEEL
prolothar_process_discovery-6.0.0.dist-info/top_level.txt
prolothar_process_discovery-6.0.0.dist-info/RECORD
