Metadata-Version: 2.1
Name: prolothar-process-discovery
Version: 6.0.0
Summary: algorithms for process mining and data mining on event sequences
Home-page: https://github.com/shs-it/prolothar-process-discovery
Author: Boris Wiegand
Author-email: boris.wiegand@stahl-holding-saar.de
License: GNU GENERAL PUBLIC LICENSE
Classifier: Programming Language :: Python :: 3
License-File: LICENSE
Requires-Dist: prolothar-common <7,>=6.0.0
Requires-Dist: strsimpy ==0.1.3
Requires-Dist: pqdict >=1.3.0
Requires-Dist: pulp <3,>=2.1
Requires-Dist: tqdm <5,>=4.54.1
